docs_ranking_metrics/__init__.py
docs_ranking_metrics/evaluation_metrics.py
docs_ranking_metrics/models.py
docs_ranking_metrics/ranking_metrics.py
docs_ranking_metrics-0.0.4.dist-info/METADATA
docs_ranking_metrics-0.0.4.dist-info/WHEEL
docs_ranking_metrics-0.0.4.dist-info/top_level.txt
docs_ranking_metrics-0.0.4.dist-info/RECORD
