Metadata-Version: 2.1
Name: docs-ranking-metrics
Version: 0.0.4
Summary: The package contains functions for calculating ranking metrics
Home-page: https://github.com/betepok506/RankingMetrics
Author: Andrey Rotanov
Author-email: rotanov07@mail.ru
License: UNKNOWN
Keywords: test
Platform: UNKNOWN
Classifier: Development Status :: 4 - Beta
Classifier: Intended Audience :: Developers
Classifier: License :: OSI Approved :: MIT License
Classifier: Programming Language :: Python :: 3
Classifier: Operating System :: OS Independent
Requires-Python: >=3.7, <4
Requires-Dist: rank-bm25 (>=0.2.2)
Requires-Dist: sentence-transformers (>=2.2.2)
Requires-Dist: numpy
Requires-Dist: tensorflow-text
Provides-Extra: all
Provides-Extra: test
Requires-Dist: coverage ; extra == 'test'
